{
  "meta": {
    "created_date": "2024-09-17T22:44:21",
    "updated_date": "2024-09-17T22:44:21",
    "field_reference": "https://developer.wordpress.org/rest-api/reference/media/",
    "api_version": "v2",
    "api_url": "https://live-digital-ca-gov.pantheonsite.io/wp-json/wp/v2/",
    "object_url": "https://live-digital-ca-gov.pantheonsite.io/wp-json/wp/v2/media/2190",
    "process": {
      "source_code": "https://github.com/cagov/wordpress-to-github",
      "source_data": "https://live-digital-ca-gov.pantheonsite.io",
      "deployment_target": "https://github.com/cagov/digital.ca.gov/tree/main"
    },
    "refresh_frequency": "as needed"
  },
  "data": {
    "id": 2190,
    "date": "2024-09-17T15:44:21",
    "date_gmt": "2024-09-17T22:44:21",
    "guid": "https://live-digital-ca-gov.pantheonsite.io/wp-content/uploads/2024/09/job-posting-header-product-mgr.webp",
    "modified": "2024-09-17T15:44:21",
    "modified_gmt": "2024-09-17T22:44:21",
    "slug": "job-posting-header-product-mgr",
    "status": "inherit",
    "type": "attachment",
    "link": "https://live-digital-ca-gov.pantheonsite.io/job-posting-header-product-mgr/",
    "title": "job-posting-header-product-mgr",
    "author": "Jim Bumgardner",
    "featured_media": 0,
    "comment_status": "closed",
    "ping_status": "closed",
    "template": "",
    "meta": [],
    "categories": [
      1
    ],
    "description": "<p class=\"attachment\"><a href='https://live-digital-ca-gov.pantheonsite.io/wp-content/uploads/2024/09/job-posting-header-product-mgr.webp'><img loading=\"lazy\" decoding=\"async\" width=\"576\" height=\"156\" src=\"https://live-digital-ca-gov.pantheonsite.io/wp-content/uploads/2024/09/job-posting-header-product-mgr-576x156.webp\" class=\"attachment-medium size-medium\" alt=\"\" srcset=\"https://live-digital-ca-gov.pantheonsite.io/wp-content/uploads/2024/09/job-posting-header-product-mgr-576x156.webp 576w, https://live-digital-ca-gov.pantheonsite.io/wp-content/uploads/2024/09/job-posting-header-product-mgr-768x208.webp 768w, https://live-digital-ca-gov.pantheonsite.io/wp-content/uploads/2024/09/job-posting-header-product-mgr.webp 1024w\" sizes=\"(max-width: 576px) 100vw, 576px\" /></a></p>\n",
    "caption": "",
    "alt_text": "",
    "media_type": "image",
    "mime_type": "image/webp",
    "media_details": {
      "width": 1024,
      "height": 277,
      "file": "2024/09/job-posting-header-product-mgr.webp",
      "filesize": 17196,
      "sizes": {
        "medium": {
          "file": "job-posting-header-product-mgr-576x156.webp",
          "width": 576,
          "height": 156,
          "filesize": 9638,
          "mime_type": "image/webp",
          "source_url": "https://live-digital-ca-gov.pantheonsite.io/wp-content/uploads/2024/09/job-posting-header-product-mgr-576x156.webp"
        },
        "thumbnail": {
          "file": "job-posting-header-product-mgr-150x150.webp",
          "width": 150,
          "height": 150,
          "filesize": 1520,
          "mime_type": "image/webp",
          "source_url": "https://live-digital-ca-gov.pantheonsite.io/wp-content/uploads/2024/09/job-posting-header-product-mgr-150x150.webp"
        },
        "medium_large": {
          "file": "job-posting-header-product-mgr-768x208.webp",
          "width": 768,
          "height": 208,
          "filesize": 14810,
          "mime_type": "image/webp",
          "source_url": "https://live-digital-ca-gov.pantheonsite.io/wp-content/uploads/2024/09/job-posting-header-product-mgr-768x208.webp"
        },
        "full": {
          "file": "job-posting-header-product-mgr.webp",
          "width": 1024,
          "height": 277,
          "mime_type": "image/webp",
          "source_url": "https://live-digital-ca-gov.pantheonsite.io/wp-content/uploads/2024/09/job-posting-header-product-mgr.webp"
        }
      },
      "image_meta": {
        "aperture": "0",
        "credit": "",
        "camera": "",
        "caption": "",
        "created_timestamp": "0",
        "copyright": "",
        "focal_length": "0",
        "iso": "0",
        "shutter_speed": "0",
        "title": "",
        "orientation": "0",
        "keywords": []
      }
    },
    "post": null,
    "source_url": "https://live-digital-ca-gov.pantheonsite.io/wp-content/uploads/2024/09/job-posting-header-product-mgr.webp",
    "wordpress_url": "https://live-digital-ca-gov.pantheonsite.io/wp-content/uploads/2024/09/job-posting-header-product-mgr.webp",
    "sizes": [
      {
        "type": "full",
        "path": "2024/09/job-posting-header-product-mgr.webp",
        "wordpress_url": "https://live-digital-ca-gov.pantheonsite.io/wp-content/uploads/2024/09/job-posting-header-product-mgr.webp",
        "file": "job-posting-header-product-mgr.webp",
        "width": 1024,
        "height": 277,
        "mime_type": "image/webp",
        "source_url": "https://live-digital-ca-gov.pantheonsite.io/wp-content/uploads/2024/09/job-posting-header-product-mgr.webp"
      },
      {
        "type": "medium_large",
        "path": "2024/09/job-posting-header-product-mgr-768x208.webp",
        "wordpress_url": "https://live-digital-ca-gov.pantheonsite.io/wp-content/uploads/2024/09/job-posting-header-product-mgr-768x208.webp",
        "file": "job-posting-header-product-mgr-768x208.webp",
        "width": 768,
        "height": 208,
        "filesize": 14810,
        "mime_type": "image/webp",
        "source_url": "https://live-digital-ca-gov.pantheonsite.io/wp-content/uploads/2024/09/job-posting-header-product-mgr-768x208.webp"
      },
      {
        "type": "medium",
        "path": "2024/09/job-posting-header-product-mgr-576x156.webp",
        "wordpress_url": "https://live-digital-ca-gov.pantheonsite.io/wp-content/uploads/2024/09/job-posting-header-product-mgr-576x156.webp",
        "file": "job-posting-header-product-mgr-576x156.webp",
        "width": 576,
        "height": 156,
        "filesize": 9638,
        "mime_type": "image/webp",
        "source_url": "https://live-digital-ca-gov.pantheonsite.io/wp-content/uploads/2024/09/job-posting-header-product-mgr-576x156.webp"
      },
      {
        "type": "thumbnail",
        "path": "2024/09/job-posting-header-product-mgr-150x150.webp",
        "wordpress_url": "https://live-digital-ca-gov.pantheonsite.io/wp-content/uploads/2024/09/job-posting-header-product-mgr-150x150.webp",
        "file": "job-posting-header-product-mgr-150x150.webp",
        "width": 150,
        "height": 150,
        "filesize": 1520,
        "mime_type": "image/webp",
        "source_url": "https://live-digital-ca-gov.pantheonsite.io/wp-content/uploads/2024/09/job-posting-header-product-mgr-150x150.webp"
      }
    ],
    "path": "2024/09/job-posting-header-product-mgr.webp"
  }
}