{
  "meta": {
    "created_date": "2026-02-26T17:56:22",
    "updated_date": "2026-02-26T17:56:53",
    "field_reference": "https://developer.wordpress.org/rest-api/reference/media/",
    "api_version": "v2",
    "api_url": "https://live-digital-ca-gov.pantheonsite.io/wp-json/wp/v2/",
    "object_url": "https://live-digital-ca-gov.pantheonsite.io/wp-json/wp/v2/media/3345",
    "process": {
      "source_code": "https://github.com/cagov/wordpress-to-github",
      "source_data": "https://live-digital-ca-gov.pantheonsite.io",
      "deployment_target": "https://github.com/cagov/digital.ca.gov/tree/main"
    },
    "refresh_frequency": "as needed"
  },
  "data": {
    "id": 3345,
    "date": "2026-02-26T09:56:22",
    "date_gmt": "2026-02-26T17:56:22",
    "guid": "https://live-digital-ca-gov.pantheonsite.io/wp-content/uploads/2026/02/bppe-case-study-cover.jpg",
    "modified": "2026-02-26T09:56:53",
    "modified_gmt": "2026-02-26T17:56:53",
    "slug": "bppe-case-study-cover",
    "status": "inherit",
    "type": "attachment",
    "link": "https://live-digital-ca-gov.pantheonsite.io/bppe-case-study-cover/",
    "title": "bppe-case-study-cover",
    "author": "Michael Sullivan",
    "featured_media": 0,
    "comment_status": "closed",
    "ping_status": "closed",
    "template": "",
    "meta": [],
    "categories": [
      1
    ],
    "class_list": [
      "post-3345",
      "attachment",
      "type-attachment",
      "status-inherit",
      "hentry",
      "category-uncategorized"
    ],
    "description": "<p class=\"attachment\"><a href='https://live-digital-ca-gov.pantheonsite.io/wp-content/uploads/2026/02/bppe-case-study-cover.jpg'><img loading=\"lazy\" decoding=\"async\" width=\"576\" height=\"288\" src=\"https://live-digital-ca-gov.pantheonsite.io/wp-content/uploads/2026/02/bppe-case-study-cover-576x288.jpg\" class=\"attachment-medium size-medium\" alt=\"Stacks upon stacks of paperwork\" srcset=\"https://live-digital-ca-gov.pantheonsite.io/wp-content/uploads/2026/02/bppe-case-study-cover-576x288.jpg 576w, https://live-digital-ca-gov.pantheonsite.io/wp-content/uploads/2026/02/bppe-case-study-cover-768x384.jpg 768w, https://live-digital-ca-gov.pantheonsite.io/wp-content/uploads/2026/02/bppe-case-study-cover.jpg 876w\" sizes=\"auto, (max-width: 576px) 100vw, 576px\" /></a></p>\n",
    "caption": "",
    "alt_text": "Stacks upon stacks of paperwork",
    "media_type": "image",
    "mime_type": "image/jpeg",
    "media_details": {
      "width": 876,
      "height": 438,
      "file": "2026/02/bppe-case-study-cover.jpg",
      "filesize": 467030,
      "sizes": {
        "medium": {
          "file": "bppe-case-study-cover-576x288.jpg",
          "width": 576,
          "height": 288,
          "filesize": 43395,
          "mime_type": "image/jpeg",
          "source_url": "https://live-digital-ca-gov.pantheonsite.io/wp-content/uploads/2026/02/bppe-case-study-cover-576x288.jpg"
        },
        "thumbnail": {
          "file": "bppe-case-study-cover-150x150.jpg",
          "width": 150,
          "height": 150,
          "filesize": 8093,
          "mime_type": "image/jpeg",
          "source_url": "https://live-digital-ca-gov.pantheonsite.io/wp-content/uploads/2026/02/bppe-case-study-cover-150x150.jpg"
        },
        "medium_large": {
          "file": "bppe-case-study-cover-768x384.jpg",
          "width": 768,
          "height": 384,
          "filesize": 70429,
          "mime_type": "image/jpeg",
          "source_url": "https://live-digital-ca-gov.pantheonsite.io/wp-content/uploads/2026/02/bppe-case-study-cover-768x384.jpg"
        },
        "full": {
          "file": "bppe-case-study-cover.jpg",
          "width": 876,
          "height": 438,
          "mime_type": "image/jpeg",
          "source_url": "https://live-digital-ca-gov.pantheonsite.io/wp-content/uploads/2026/02/bppe-case-study-cover.jpg"
        }
      },
      "image_meta": {
        "aperture": "0",
        "credit": "",
        "camera": "",
        "caption": "",
        "created_timestamp": "0",
        "copyright": "",
        "focal_length": "0",
        "iso": "0",
        "shutter_speed": "0",
        "title": "",
        "orientation": "0",
        "keywords": []
      }
    },
    "post": null,
    "source_url": "https://live-digital-ca-gov.pantheonsite.io/wp-content/uploads/2026/02/bppe-case-study-cover.jpg",
    "wordpress_url": "https://live-digital-ca-gov.pantheonsite.io/wp-content/uploads/2026/02/bppe-case-study-cover.jpg",
    "sizes": [
      {
        "type": "full",
        "path": "2026/02/bppe-case-study-cover.jpg",
        "wordpress_url": "https://live-digital-ca-gov.pantheonsite.io/wp-content/uploads/2026/02/bppe-case-study-cover.jpg",
        "file": "bppe-case-study-cover.jpg",
        "width": 876,
        "height": 438,
        "mime_type": "image/jpeg",
        "source_url": "https://live-digital-ca-gov.pantheonsite.io/wp-content/uploads/2026/02/bppe-case-study-cover.jpg"
      },
      {
        "type": "medium_large",
        "path": "2026/02/bppe-case-study-cover-768x384.jpg",
        "wordpress_url": "https://live-digital-ca-gov.pantheonsite.io/wp-content/uploads/2026/02/bppe-case-study-cover-768x384.jpg",
        "file": "bppe-case-study-cover-768x384.jpg",
        "width": 768,
        "height": 384,
        "filesize": 70429,
        "mime_type": "image/jpeg",
        "source_url": "https://live-digital-ca-gov.pantheonsite.io/wp-content/uploads/2026/02/bppe-case-study-cover-768x384.jpg"
      },
      {
        "type": "medium",
        "path": "2026/02/bppe-case-study-cover-576x288.jpg",
        "wordpress_url": "https://live-digital-ca-gov.pantheonsite.io/wp-content/uploads/2026/02/bppe-case-study-cover-576x288.jpg",
        "file": "bppe-case-study-cover-576x288.jpg",
        "width": 576,
        "height": 288,
        "filesize": 43395,
        "mime_type": "image/jpeg",
        "source_url": "https://live-digital-ca-gov.pantheonsite.io/wp-content/uploads/2026/02/bppe-case-study-cover-576x288.jpg"
      },
      {
        "type": "thumbnail",
        "path": "2026/02/bppe-case-study-cover-150x150.jpg",
        "wordpress_url": "https://live-digital-ca-gov.pantheonsite.io/wp-content/uploads/2026/02/bppe-case-study-cover-150x150.jpg",
        "file": "bppe-case-study-cover-150x150.jpg",
        "width": 150,
        "height": 150,
        "filesize": 8093,
        "mime_type": "image/jpeg",
        "source_url": "https://live-digital-ca-gov.pantheonsite.io/wp-content/uploads/2026/02/bppe-case-study-cover-150x150.jpg"
      }
    ],
    "path": "2026/02/bppe-case-study-cover.jpg"
  }
}