{
  "meta": {
    "created_date": "2023-01-04T19:02:28",
    "updated_date": "2023-01-28T00:13:42",
    "field_reference": "https://developer.wordpress.org/rest-api/reference/pages/",
    "api_version": "v2",
    "api_url": "https://live-digital-ca-gov.pantheonsite.io/wp-json/wp/v2/",
    "process": {
      "source_code": "https://github.com/cagov/wordpress-to-github",
      "source_data": "https://live-digital-ca-gov.pantheonsite.io",
      "deployment_target": "https://github.com/cagov/digital.ca.gov/tree/main"
    },
    "refresh_frequency": "as needed"
  },
  "data": {
    "id": 990,
    "date": "2023-01-04T11:02:28",
    "date_gmt": "2023-01-04T19:02:28",
    "guid": "https://live-digital-ca-gov.pantheonsite.io/?page_id=990",
    "modified": "2023-01-27T16:13:42",
    "modified_gmt": "2023-01-28T00:13:42",
    "slug": "principal-analytics-engineer",
    "status": "publish",
    "type": "page",
    "link": "https://live-digital-ca-gov.pantheonsite.io/join-us/principal-analytics-engineer/",
    "title": "Principal Analytics Engineer",
    "excerpt": "<p>As our Principal Analytics Engineer, you will serve as the lead developer of efficient, flexible, and actionable data models for a variety of analytic purposes. You will take a lead role in developing and executing modern analytic engineering patterns for the State of California. You will use cloud-based tools and SQL-driven coding practices with dbt &#8230; <a title=\"Principal Analytics Engineer\" class=\"read-more\" href=\"https://live-digital-ca-gov.pantheonsite.io/join-us/principal-analytics-engineer/\" aria-label=\"More on Principal Analytics Engineer\">Read more</a></p>\n",
    "author": "Ashley Lanham",
    "featured_media": 0,
    "parent": 238,
    "menu_order": 0,
    "comment_status": "closed",
    "ping_status": "closed",
    "template": "",
    "meta": [],
    "categories": [],
    "tags": [],
    "design_system_fields": {
      "template": "page"
    },
    "og_meta": {
      "editor": {
        "platform": "WordPress",
        "plugin": "autodescription",
        "plugin_name": "The SEO Framework",
        "plugin_version": "4.1.5.1",
        "editor_url": "https://live-digital-ca-gov.pantheonsite.io"
      },
      "site_name": "innovation.ca.gov",
      "site_description": "Office of Data &amp; Innovation",
      "site_url": "https://live-digital-ca-gov.pantheonsite.io",
      "canonical_url": "https://live-digital-ca-gov.pantheonsite.io/join-us/principal-analytics-engineer/",
      "page_title": "Principal Analytics Engineer",
      "page_description": "Office of Data &amp; Innovation",
      "page_social_image_url": "",
      "page_social_image_width": 1200,
      "page_social_image_height": 630,
      "page_social_image_alt": "",
      "meta_title": "Principal Analytics Engineer",
      "meta_description": "As our Principal Analytics Engineer, you will serve as the lead developer of efficient, flexible, and actionable data models for a variety of analytic purposes.",
      "meta_canonical_url": "https://live-digital-ca-gov.pantheonsite.io/join-us/principal-analytics-engineer/",
      "open_graph_title": "Principal Analytics Engineer",
      "open_graph_description": "Office of Data &amp; Innovation",
      "twitter_title": "Principal Analytics Engineer",
      "twitter_description": "Office of Data &amp; Innovation"
    },
    "headless_categories": [],
    "headless_tags": [],
    "headless_publishing": [],
    "headless_preview": [],
    "wordpress_url": "https://live-digital-ca-gov.pantheonsite.io/join-us/principal-analytics-engineer/"
  }
}